MANIFEST.in
README.md
setup.py
django_guac_auth.egg-info/PKG-INFO
django_guac_auth.egg-info/SOURCES.txt
django_guac_auth.egg-info/dependency_links.txt
django_guac_auth.egg-info/not-zip-safe
django_guac_auth.egg-info/requires.txt
django_guac_auth.egg-info/top_level.txt
guac_auth/__init__.py
guac_auth/fields.py
guac_auth/models.py
guac_auth/tests.py
guac_auth/utils.py
guac_auth/migrations/0001_initial.py
guac_auth/migrations/0002_auto_20160128_1752.py
guac_auth/migrations/0003_auto_20160128_1757.py
guac_auth/migrations/__init__.py
requirements/common.txt
requirements/development.txt
requirements/production.txt
requirements/testing.txt