Metadata-Version: 1.0
Name: django-guac-auth
Version: 1.0.0
Summary: Django app to enable Guacamole authentication
Home-page: UNKNOWN
Author: Nimbis Services, Inc.
Author-email: devops@nimbisservices.com
License: BSD
Platform: UNKNOWN
